plyght/__init__.py
plyght/config/__init__.py
plyght/config/auto.py
plyght/config/base_config.py
plyght/config/clients/__init__.py
plyght/config/clients/client.py
plyght/config/clients/exceptions.py
plyght/config/clients/kafka_client.py
plyght/config/clients/neo4j_client.py
plyght/config/clients/opensearch_client.py
plyght/config/clients/s3_client.py
plyght/core/__init__.py
plyght/core/functions/__init__.py
plyght/core/functions/decorators.py
plyght/util/__init__.py
plyght/util/converters/__init__.py
plyght/util/converters/case.py
plyght/util/logging/__init__.py
plyght/util/logging/formatter.py
plyght/util/logging/logger.py
plyght-0.1.1a2.dist-info/METADATA
plyght-0.1.1a2.dist-info/WHEEL
plyght-0.1.1a2.dist-info/RECORD
