Metadata-Version: 2.3
Name: Plyght
Version: 0.1.1a2
Summary: 
License: .github/LICENSE
Keywords: python,utility,modern,neo4j,kafka,opensearch,s3
Author: Parker
Maintainer: Parker
Requires-Python: >=3.9,<4
Classifier: Development Status :: 1 - Planning
Classifier: Intended Audience :: Developers
Classifier: Topic :: Database
Classifier: Topic :: Software Development :: Libraries :: Python Modules
Classifier: Programming Language :: Python :: 3
Classifier: License :: OSI Approved :: Apache Software License
Classifier: Operating System :: OS Independent
Provides-Extra: boto
Provides-Extra: kafka
Provides-Extra: neo4j
Provides-Extra: opensearch
Requires-Dist: boto3 (>=1.37.20) ; extra == "boto"
Requires-Dist: boto3 (>=1.37.20) ; extra == "boto"
Requires-Dist: kafka-python (>=2.1.3) ; extra == "kafka"
Requires-Dist: kafka-python (>=2.1.3) ; extra == "kafka"
Requires-Dist: neo4j (>=5.28.1) ; extra == "neo4j"
Requires-Dist: neo4j (>=5.28.1) ; extra == "neo4j"
Requires-Dist: opensearch-py (>=2.8.0) ; extra == "opensearch"
Requires-Dist: opensearch-py (>=2.8.0) ; extra == "opensearch"
Project-URL: Documentation, https://plyght.teampixl.info
Project-URL: Issues, https://github.com/parkermmr/plyght/issues
Project-URL: Repository, https://github.com/parkermmr/plyght
